better_bundle_config/__init__.py
better_bundle_config/config.yml
better_bundle_config-0.1.3.dist-info/METADATA
better_bundle_config-0.1.3.dist-info/WHEEL
better_bundle_config-0.1.3.dist-info/entry_points.txt
better_bundle_config-0.1.3.dist-info/RECORD
