Metadata-Version: 2.4
Name: better-bundle-config
Version: 0.1.3
Author-email: Michael Gardner <gardnmi@gmail.com>
License: MIT
Requires-Python: >=3.10
Requires-Dist: databricks-sdk>=0.44.1
Requires-Dist: loguru>=0.7.3
Requires-Dist: pyyaml>=6.0.2
Requires-Dist: ruff>=0.11.2
Provides-Extra: dev
Requires-Dist: databricks-connect==15.4.*; extra == 'dev'
